{
  "source": "analysis/mms_zoom_2300_state.json",
  "target_ann": "analysis/mms_20170913_ann.hnsw",
  "target_meta": "analysis/mms_20170913_ann.meta",
  "target_state": "analysis/mms_20170913_state.json",
  "profile": "coh>=P60,stab>=P60,ent<=P40,lambda<=P70",
  "parameters": {
    "min_connector": 0.0,
    "min_patternability": 0.0,
    "min_occurrences": 1,
    "sort": "patternability",
    "limit": null,
    "k": 50,
    "max_distance": null
  },
  "candidate_count": 1,
  "results": [
    {
      "string": "mms1_fgm_b_gse_srvy_l2_y__zpos",
      "occurrences": 895,
      "patternability": 0.45933974050387044,
      "connector": 0.5,
      "metrics": {
        "coherence": 0.007226290272639219,
        "stability": 0.46388122605606347,
        "entropy": 0.9927737097273609,
        "rupture": 0.5361187739439366,
        "lambda_hazard": 0.5361187739439366,
        "patternability": 0.45933974050387044,
        "connector": 0.5
      },
      "window_ids": [
        0,
        23,
        24,
        25,
        26,
        27,
        28,
        29,
        30,
        32,
        33,
        38,
        39,
        40,
        45,
        46,
        49,
        50,
        164,
        165,
        182,
        183,
        194,
        195,
        206,
        207,
        305,
        306,
        310,
        311,
        312,
        313,
        319,
        339,
        340,
        341,
        342,
        343,
        344,
        345,
        348,
        349,
        354,
        355,
        356,
        357,
        362,
        363,
        364,
        365,
        366,
        367,
        368,
        370,
        371,
        376,
        377,
        378,
        379,
        380,
        381,
        382,
        383,
        384,
        385,
        386,
        395,
        396,
        397,
        398,
        399,
        400,
        411,
        412,
        413,
        414,
        415,
        416,
        417,
        418,
        419,
        422,
        423,
        424,
        425,
        426,
        427,
        428,
        429,
        430,
        431,
        432,
        433,
        434,
        435,
        436,
        437,
        438,
        439,
        442,
        443,
        445,
        446,
        447,
        448,
        455,
        456,
        457,
        458,
        459,
        460,
        461,
        462,
        463,
        464,
        465,
        466,
        467,
        469,
        470,
        471,
        472,
        473,
        474,
        475,
        479,
        480,
        481,
        482,
        485,
        486,
        490,
        491,
        492,
        493,
        494,
        496,
        497,
        498,
        500,
        501,
        505,
        506,
        507,
        508,
        515,
        516,
        517,
        518,
        519,
        520,
        521,
        522,
        530,
        531,
        532,
        533,
        535,
        536,
        537,
        538,
        539,
        540,
        541,
        542,
        543,
        544,
        545,
        546,
        547,
        548,
        549,
        554,
        555,
        556,
        558,
        559,
        560,
        561,
        562,
        563,
        564,
        565,
        566,
        567,
        568,
        569,
        570,
        572,
        573,
        574,
        575,
        576,
        577,
        578,
        579,
        580,
        581,
        582,
        583,
        591,
        592,
        593,
        594,
        595,
        596,
        597,
        598,
        599,
        600,
        603,
        604,
        605,
        606,
        607,
        608,
        609,
        610,
        611,
        612,
        613,
        614,
        615,
        616,
        617,
        618,
        627,
        628,
        629,
        630,
        631,
        632,
        640,
        641,
        642,
        643,
        644,
        645,
        646,
        647,
        648,
        649,
        650,
        651,
        652,
        658,
        659,
        660,
        661,
        662,
        663,
        664,
        665,
        666,
        667,
        668,
        669,
        670,
        671,
        672,
        673,
        674,
        675,
        676,
        677,
        682,
        683,
        684,
        685,
        686,
        687,
        688,
        689,
        690,
        691,
        694,
        695,
        705,
        706,
        707,
        708,
        709,
        710,
        711,
        712,
        713,
        714,
        715,
        716,
        717,
        718,
        719,
        720,
        721,
        722,
        731,
        732,
        733,
        734,
        735,
        736,
        737,
        738,
        739,
        740,
        741,
        742,
        743,
        744,
        745,
        751,
        752,
        753,
        754,
        755,
        759,
        760,
        761,
        762,
        763,
        764,
        765,
        766,
        767,
        768,
        769,
        770,
        771,
        773,
        774,
        775,
        776,
        777,
        778,
        779,
        780,
        781,
        787,
        788,
        789,
        790,
        791,
        792,
        793,
        794,
        795,
        796,
        797,
        798,
        799,
        800,
        801,
        802,
        803,
        815,
        816,
        817,
        818,
        819,
        820,
        821,
        822,
        823,
        824,
        825,
        826,
        827,
        828,
        829,
        830,
        831,
        832,
        841,
        842,
        843,
        844,
        845,
        846,
        847,
        848,
        849,
        850,
        851,
        852,
        853,
        859,
        860,
        865,
        866,
        867,
        868,
        869,
        870,
        871,
        872,
        873,
        874,
        875,
        876,
        877,
        878,
        879,
        880,
        881,
        882,
        883,
        884,
        885,
        886,
        890,
        891,
        903,
        904,
        905,
        906,
        907,
        908,
        909,
        910,
        911,
        912,
        913,
        924,
        925,
        926,
        927,
        928,
        929,
        930,
        931,
        932,
        933,
        934,
        935,
        936,
        937,
        938,
        939,
        943,
        944,
        945,
        946,
        947,
        948,
        949,
        950,
        951,
        952,
        953,
        954,
        955,
        961,
        962,
        963,
        964,
        965,
        966,
        967,
        968,
        971,
        972,
        978,
        979,
        980,
        981,
        982,
        983,
        987,
        988,
        989,
        990,
        991,
        992,
        993,
        994,
        995,
        996,
        997,
        998,
        999,
        1000,
        1001,
        1002,
        1003,
        1004,
        1005,
        1006,
        1007,
        1009,
        1010,
        1011,
        1012,
        1013,
        1021,
        1022,
        1023,
        1024,
        1025,
        1030,
        1031,
        1032,
        1040,
        1041,
        1042,
        1043,
        1044,
        1045,
        1046,
        1047,
        1048,
        1049,
        1050,
        1051,
        1052,
        1053,
        1054,
        1055,
        1056,
        1062,
        1063,
        1064,
        1065,
        1066,
        1067,
        1068,
        1069,
        1070,
        1071,
        1072,
        1076,
        1077,
        1078,
        1079,
        1080,
        1081,
        1089,
        1090,
        1091,
        1099,
        1100,
        1101,
        1102,
        1103,
        1104,
        1105,
        1106,
        1107,
        1108,
        1109,
        1110,
        1111,
        1112,
        1113,
        1114,
        1115,
        1116,
        1119,
        1120,
        1123,
        1124,
        1125,
        1130,
        1131,
        1132,
        1133,
        1134,
        1135,
        1136,
        1140,
        1141,
        1142,
        1143,
        1144,
        1145,
        1146,
        1150,
        1151,
        1152,
        1153,
        1154
      ],
      "matches": [
        {
          "window_id": 5290,
          "distance": 0.0010418359888717532,
          "metrics": {
            "coherence": 0.01116820766168758,
            "stability": 0.48223660114760103,
            "entropy": 0.9888317923383124,
            "rupture": 0.517763398852399,
            "lambda_hazard": 0.517763398852399,
            "patternability": 0.0,
            "connector": 0.0
          },
          "signature": "c0.01_s0.48_e0.99",
          "window_start": 2708480,
          "window_end": 2709504
        },
        {
          "window_id": 3228,
          "distance": 0.0016668972093611956,
          "metrics": {
            "coherence": 0.011080388337823655,
            "stability": 0.48724209498229765,
            "entropy": 0.9889196116621763,
            "rupture": 0.5127579050177024,
            "lambda_hazard": 0.5127579050177024,
            "patternability": 0.0,
            "connector": 0.0
          },
          "signature": "c0.01_s0.49_e0.99",
          "window_start": 1652736,
          "window_end": 1653760
        },
        {
          "window_id": 5289,
          "distance": 0.0017158163245767355,
          "metrics": {
            "coherence": 0.011928781721332937,
            "stability": 0.48748626541325846,
            "entropy": 0.9880712182786671,
            "rupture": 0.5125137345867415,
            "lambda_hazard": 0.5125137345867415,
            "patternability": 0.0,
            "connector": 0.0
          },
          "signature": "c0.01_s0.49_e0.99",
          "window_start": 2707968,
          "window_end": 2708992
        },
        {
          "window_id": 3227,
          "distance": 0.0017938263481482863,
          "metrics": {
            "coherence": 0.011389284517053455,
            "stability": 0.4880966914906605,
            "entropy": 0.9886107154829465,
            "rupture": 0.5119033085093395,
            "lambda_hazard": 0.5119033085093395,
            "patternability": 0.0,
            "connector": 0.0
          },
          "signature": "c0.01_s0.49_e0.99",
          "window_start": 1652224,
          "window_end": 1653248
        },
        {
          "window_id": 3226,
          "distance": 0.0018309771548956633,
          "metrics": {
            "coherence": 0.011478326791109272,
            "stability": 0.4883408619216213,
            "entropy": 0.9885216732088907,
            "rupture": 0.5116591380783787,
            "lambda_hazard": 0.5116591380783787,
            "patternability": 0.0,
            "connector": 0.0
          },
          "signature": "c0.01_s0.49_e0.99",
          "window_start": 1651712,
          "window_end": 1652736
        },
        {
          "window_id": 5291,
          "distance": 0.0018497018609195948,
          "metrics": {
            "coherence": 0.011522978992444921,
            "stability": 0.4884629471371017,
            "entropy": 0.9884770210075551,
            "rupture": 0.5115370528628983,
            "lambda_hazard": 0.5115370528628983,
            "patternability": 0.0,
            "connector": 0.0
          },
          "signature": "c0.01_s0.49_e0.99",
          "window_start": 2708992,
          "window_end": 2710016
        },
        {
          "window_id": 6706,
          "distance": 0.0018594833090901375,
          "metrics": {
            "coherence": 0.009518694709754083,
            "stability": 0.4887071175680625,
            "entropy": 0.9904813052902459,
            "rupture": 0.5112928824319375,
            "lambda_hazard": 0.5112928824319375,
            "patternability": 0.0,
            "connector": 0.0
          },
          "signature": "c0.01_s0.49_e0.99",
          "window_start": 3433472,
          "window_end": 3434496
        },
        {
          "window_id": 3218,
          "distance": 0.001860352116636932,
          "metrics": {
            "coherence": 0.012950567024397674,
            "stability": 0.4883408619216213,
            "entropy": 0.9870494329756023,
            "rupture": 0.5116591380783787,
            "lambda_hazard": 0.5116591380783787,
            "patternability": 0.0,
            "connector": 0.0
          },
          "signature": "c0.01_s0.49_e0.99",
          "window_start": 1647616,
          "window_end": 1648640
        },
        {
          "window_id": 9481,
          "distance": 0.0019308053888380527,
          "metrics": {
            "coherence": 0.01362285497309923,
            "stability": 0.4887071175680625,
            "entropy": 0.9863771450269008,
            "rupture": 0.5112928824319375,
            "lambda_hazard": 0.5112928824319375,
            "patternability": 0.0,
            "connector": 0.0
          },
          "signature": "c0.01_s0.49_e0.99",
          "window_start": 4854272,
          "window_end": 4855296
        },
        {
          "window_id": 3225,
          "distance": 0.001986972987651825,
          "metrics": {
            "coherence": 0.012019921728367522,
            "stability": 0.48931754364546454,
            "entropy": 0.9879800782716325,
            "rupture": 0.5106824563545355,
            "lambda_hazard": 0.5106824563545355,
            "patternability": 0.0,
            "connector": 0.0
          },
          "signature": "c0.01_s0.49_e0.99",
          "window_start": 1651200,
          "window_end": 1652224
        },
        {
          "window_id": 3260,
          "distance": 0.001993522746488452,
          "metrics": {
            "coherence": 0.00997050960660828,
            "stability": 0.48956171407642535,
            "entropy": 0.9900294903933917,
            "rupture": 0.5104382859235747,
            "lambda_hazard": 0.5104382859235747,
            "patternability": 0.0,
            "connector": 0.0
          },
          "signature": "c0.01_s0.49_e0.99",
          "window_start": 1669120,
          "window_end": 1670144
        },
        {
          "window_id": 6135,
          "distance": 0.0019935304298996925,
          "metrics": {
            "coherence": 0.013188698958965794,
            "stability": 0.48919545842998413,
            "entropy": 0.9868113010410342,
            "rupture": 0.5108045415700159,
            "lambda_hazard": 0.5108045415700159,
            "patternability": 0.0,
            "connector": 0.0
          },
          "signature": "c0.01_s0.49_e0.99",
          "window_start": 3141120,
          "window_end": 3142144
        },
        {
          "window_id": 3275,
          "distance": 0.0020128381438553333,
          "metrics": {
            "coherence": 0.010012106749828664,
            "stability": 0.48968379929190575,
            "entropy": 0.9899878932501713,
            "rupture": 0.5103162007080942,
            "lambda_hazard": 0.5103162007080942,
            "patternability": 0.0,
            "connector": 0.0
          },
          "signature": "c0.01_s0.49_e0.99",
          "window_start": 1676800,
          "window_end": 1677824
        },
        {
          "window_id": 3274,
          "distance": 0.0021268613636493683,
          "metrics": {
            "coherence": 0.011344894433432895,
            "stability": 0.4902942253693078,
            "entropy": 0.9886551055665671,
            "rupture": 0.5097057746306922,
            "lambda_hazard": 0.5097057746306922,
            "patternability": 0.0,
            "connector": 0.0
          },
          "signature": "c0.01_s0.49_e0.99",
          "window_start": 1676288,
          "window_end": 1677312
        },
        {
          "window_id": 3091,
          "distance": 0.002162270015105605,
          "metrics": {
            "coherence": 0.009559332998468895,
            "stability": 0.490660481015749,
            "entropy": 0.9904406670015311,
            "rupture": 0.509339518984251,
            "lambda_hazard": 0.509339518984251,
            "patternability": 0.0,
            "connector": 0.0
          },
          "signature": "c0.01_s0.49_e0.99",
          "window_start": 1582592,
          "window_end": 1583616
        },
        {
          "window_id": 6676,
          "distance": 0.002168690785765648,
          "metrics": {
            "coherence": 0.013380781052900526,
            "stability": 0.4902942253693078,
            "entropy": 0.9866192189470995,
            "rupture": 0.5097057746306922,
            "lambda_hazard": 0.5097057746306922,
            "patternability": 0.0,
            "connector": 0.0
          },
          "signature": "c0.01_s0.49_e0.99",
          "window_start": 3418112,
          "window_end": 3419136
        },
        {
          "window_id": 6693,
          "distance": 0.0022469963878393173,
          "metrics": {
            "coherence": 0.012527445247224156,
            "stability": 0.4909046514467098,
            "entropy": 0.9874725547527758,
            "rupture": 0.5090953485532902,
            "lambda_hazard": 0.5090953485532902,
            "patternability": 0.0,
            "connector": 0.0
          },
          "signature": "c0.01_s0.49_e0.99",
          "window_start": 3426816,
          "window_end": 3427840
        },
        {
          "window_id": 3107,
          "distance": 0.002271693665534258,
          "metrics": {
            "coherence": 0.01047543157185582,
            "stability": 0.491270907093151,
            "entropy": 0.9895245684281442,
            "rupture": 0.508729092906849,
            "lambda_hazard": 0.508729092906849,
            "patternability": 0.0,
            "connector": 0.0
          },
          "signature": "c0.01_s0.49_e0.99",
          "window_start": 1590784,
          "window_end": 1591808
        },
        {
          "window_id": 6598,
          "distance": 0.0023068462032824755,
          "metrics": {
            "coherence": 0.011478326791109272,
            "stability": 0.4913929923086314,
            "entropy": 0.9885216732088907,
            "rupture": 0.5086070076913686,
            "lambda_hazard": 0.5086070076913686,
            "patternability": 0.0,
            "connector": 0.0
          },
          "signature": "c0.01_s0.49_e0.99",
          "window_start": 3378176,
          "window_end": 3379200
        },
        {
          "window_id": 3215,
          "distance": 0.002329366747289896,
          "metrics": {
            "coherence": 0.011612545551067721,
            "stability": 0.49151507752411183,
            "entropy": 0.9883874544489323,
            "rupture": 0.5084849224758882,
            "lambda_hazard": 0.5084849224758882,
            "patternability": 0.0,
            "connector": 0.0
          },
          "signature": "c0.01_s0.49_e0.99",
          "window_start": 1646080,
          "window_end": 1647104
        },
        {
          "window_id": 6134,
          "distance": 0.00232990481890738,
          "metrics": {
            "coherence": 0.012667698073008604,
            "stability": 0.4913929923086314,
            "entropy": 0.9873323019269914,
            "rupture": 0.5086070076913686,
            "lambda_hazard": 0.5086070076913686,
            "patternability": 0.0,
            "connector": 0.0
          },
          "signature": "c0.01_s0.49_e0.99",
          "window_start": 3140608,
          "window_end": 3141632
        },
        {
          "window_id": 6136,
          "distance": 0.002332087606191635,
          "metrics": {
            "coherence": 0.015018980670848725,
            "stability": 0.4910267366621902,
            "entropy": 0.9849810193291513,
            "rupture": 0.5089732633378098,
            "lambda_hazard": 0.5089732633378098,
            "patternability": 0.0,
            "connector": 0.0
          },
          "signature": "c0.02_s0.49_e0.98",
          "window_start": 3141632,
          "window_end": 3142656
        },
        {
          "window_id": 3128,
          "distance": 0.0023452613968402147,
          "metrics": {
            "coherence": 0.013332629127012385,
            "stability": 0.4913929923086314,
            "entropy": 0.9866673708729876,
            "rupture": 0.5086070076913686,
            "lambda_hazard": 0.5086070076913686,
            "patternability": 0.0,
            "connector": 0.0
          },
          "signature": "c0.01_s0.49_e0.99",
          "window_start": 1601536,
          "window_end": 1602560
        },
        {
          "window_id": 5037,
          "distance": 0.0023532158229500055,
          "metrics": {
            "coherence": 0.012808738613443671,
            "stability": 0.49151507752411183,
            "entropy": 0.9871912613865563,
            "rupture": 0.5084849224758882,
            "lambda_hazard": 0.5084849224758882,
            "patternability": 0.0,
            "connector": 0.0
          },
          "signature": "c0.01_s0.49_e0.99",
          "window_start": 2578944,
          "window_end": 2579968
        },
        {
          "window_id": 3262,
          "distance": 0.0023543606512248516,
          "metrics": {
            "coherence": 0.010603624960460412,
            "stability": 0.49175924795507264,
            "entropy": 0.9893963750395396,
            "rupture": 0.5082407520449274,
            "lambda_hazard": 0.5082407520449274,
            "patternability": 0.0,
            "connector": 0.0
          },
          "signature": "c0.01_s0.49_e0.99",
          "window_start": 1670144,
          "window_end": 1671168
        },
        {
          "window_id": 3217,
          "distance": 0.0023588882759213448,
          "metrics": {
            "coherence": 0.013867119924874882,
            "stability": 0.4913929923086314,
            "entropy": 0.9861328800751251,
            "rupture": 0.5086070076913686,
            "lambda_hazard": 0.5086070076913686,
            "patternability": 0.0,
            "connector": 0.0
          },
          "signature": "c0.01_s0.49_e0.99",
          "window_start": 1647104,
          "window_end": 1648128
        },
        {
          "window_id": 6672,
          "distance": 0.0023905413690954447,
          "metrics": {
            "coherence": 0.01352576252308002,
            "stability": 0.49163716273959224,
            "entropy": 0.98647423747692,
            "rupture": 0.5083628372604078,
            "lambda_hazard": 0.5083628372604078,
            "patternability": 0.0,
            "connector": 0.0
          },
          "signature": "c0.01_s0.49_e0.99",
          "window_start": 3416064,
          "window_end": 3417088
        },
        {
          "window_id": 1262,
          "distance": 0.00239551835693419,
          "metrics": {
            "coherence": 0.01372029798809038,
            "stability": 0.49163716273959224,
            "entropy": 0.9862797020119096,
            "rupture": 0.5083628372604078,
            "lambda_hazard": 0.5083628372604078,
            "patternability": 0.0,
            "connector": 0.0
          },
          "signature": "c0.01_s0.49_e0.99",
          "window_start": 646144,
          "window_end": 647168
        },
        {
          "window_id": 3229,
          "distance": 0.0024167990777641535,
          "metrics": {
            "coherence": 0.011928781721332937,
            "stability": 0.49200341838603345,
            "entropy": 0.9880712182786671,
            "rupture": 0.5079965816139665,
            "lambda_hazard": 0.5079965816139665,
            "patternability": 0.0,
            "connector": 0.0
          },
          "signature": "c0.01_s0.49_e0.99",
          "window_start": 1653248,
          "window_end": 1654272
        },
        {
          "window_id": 3261,
          "distance": 0.0024172035045921803,
          "metrics": {
            "coherence": 0.010689523566041803,
            "stability": 0.49212550360151386,
            "entropy": 0.9893104764339582,
            "rupture": 0.5078744963984861,
            "lambda_hazard": 0.5078744963984861,
            "patternability": 0.0,
            "connector": 0.0
          },
          "signature": "c0.01_s0.49_e0.99",
          "window_start": 1669632,
          "window_end": 1670656
        },
        {
          "window_id": 8918,
          "distance": 0.0024210591800510883,
          "metrics": {
            "coherence": 0.013916235905035101,
            "stability": 0.49175924795507264,
            "entropy": 0.9860837640949649,
            "rupture": 0.5082407520449274,
            "lambda_hazard": 0.5082407520449274,
            "patternability": 0.0,
            "connector": 0.0
          },
          "signature": "c0.01_s0.49_e0.99",
          "window_start": 4566016,
          "window_end": 4567040
        },
        {
          "window_id": 3259,
          "distance": 0.002423604018986225,
          "metrics": {
            "coherence": 0.011124254332409489,
            "stability": 0.49212550360151386,
            "entropy": 0.9888757456675905,
            "rupture": 0.5078744963984861,
            "lambda_hazard": 0.5078744963984861,
            "patternability": 0.0,
            "connector": 0.0
          },
          "signature": "c0.01_s0.49_e0.99",
          "window_start": 1668608,
          "window_end": 1669632
        },
        {
          "window_id": 6705,
          "distance": 0.00242682546377182,
          "metrics": {
            "coherence": 0.009763831695562608,
            "stability": 0.49224758881699426,
            "entropy": 0.9902361683044374,
            "rupture": 0.5077524111830057,
            "lambda_hazard": 0.5077524111830057,
            "patternability": 0.0,
            "connector": 0.0
          },
          "signature": "c0.01_s0.49_e0.99",
          "window_start": 3432960,
          "window_end": 3433984
        },
        {
          "window_id": 6490,
          "distance": 0.002447647973895073,
          "metrics": {
            "coherence": 0.009763831695562608,
            "stability": 0.49236967403247467,
            "entropy": 0.9902361683044374,
            "rupture": 0.5076303259675253,
            "lambda_hazard": 0.5076303259675253,
            "patternability": 0.0,
            "connector": 0.0
          },
          "signature": "c0.01_s0.49_e0.99",
          "window_start": 3322880,
          "window_end": 3323904
        },
        {
          "window_id": 6677,
          "distance": 0.0024514186661690474,
          "metrics": {
            "coherence": 0.012620859614901114,
            "stability": 0.49212550360151386,
            "entropy": 0.9873791403850989,
            "rupture": 0.5078744963984861,
            "lambda_hazard": 0.5078744963984861,
            "patternability": 0.0,
            "connector": 0.0
          },
          "signature": "c0.01_s0.49_e0.99",
          "window_start": 3418624,
          "window_end": 3419648
        },
        {
          "window_id": 4176,
          "distance": 0.002465846948325634,
          "metrics": {
            "coherence": 0.01116820766168758,
            "stability": 0.49236967403247467,
            "entropy": 0.9888317923383124,
            "rupture": 0.5076303259675253,
            "lambda_hazard": 0.5076303259675253,
            "patternability": 0.0,
            "connector": 0.0
          },
          "signature": "c0.01_s0.49_e0.99",
          "window_start": 2138112,
          "window_end": 2139136
        },
        {
          "window_id": 3122,
          "distance": 0.0024788337759673595,
          "metrics": {
            "coherence": 0.013769150972432587,
            "stability": 0.49212550360151386,
            "entropy": 0.9862308490275674,
            "rupture": 0.5078744963984861,
            "lambda_hazard": 0.5078744963984861,
            "patternability": 0.0,
            "connector": 0.0
          },
          "signature": "c0.01_s0.49_e0.99",
          "window_start": 1598464,
          "window_end": 1599488
        },
        {
          "window_id": 6694,
          "distance": 0.00248072762042284,
          "metrics": {
            "coherence": 0.012019921728367522,
            "stability": 0.49236967403247467,
            "entropy": 0.9879800782716325,
            "rupture": 0.5076303259675253,
            "lambda_hazard": 0.5076303259675253,
            "patternability": 0.0,
            "connector": 0.0
          },
          "signature": "c0.01_s0.49_e0.99",
          "window_start": 3427328,
          "window_end": 3428352
        },
        {
          "window_id": 3219,
          "distance": 0.0024939877912402153,
          "metrics": {
            "coherence": 0.012667698073008604,
            "stability": 0.49236967403247467,
            "entropy": 0.9873323019269914,
            "rupture": 0.5076303259675253,
            "lambda_hazard": 0.5076303259675253,
            "patternability": 0.0,
            "connector": 0.0
          },
          "signature": "c0.01_s0.49_e0.99",
          "window_start": 1648128,
          "window_end": 1649152
        },
        {
          "window_id": 5750,
          "distance": 0.002498926129192114,
          "metrics": {
            "coherence": 0.010560806566854652,
            "stability": 0.4926138444634355,
            "entropy": 0.9894391934331453,
            "rupture": 0.5073861555365645,
            "lambda_hazard": 0.5073861555365645,
            "patternability": 0.0,
            "connector": 0.0
          },
          "signature": "c0.01_s0.49_e0.99",
          "window_start": 2944000,
          "window_end": 2945024
        },
        {
          "window_id": 3076,
          "distance": 0.0025110766291618347,
          "metrics": {
            "coherence": 0.009804992920588562,
            "stability": 0.4927359296789159,
            "entropy": 0.9901950070794114,
            "rupture": 0.5072640703210841,
            "lambda_hazard": 0.5072640703210841,
            "patternability": 0.0,
            "connector": 0.0
          },
          "signature": "c0.01_s0.49_e0.99",
          "window_start": 1574912,
          "window_end": 1575936
        },
        {
          "window_id": 3236,
          "distance": 0.0025143842212855816,
          "metrics": {
            "coherence": 0.01156771857727168,
            "stability": 0.4926138444634355,
            "entropy": 0.9884322814227283,
            "rupture": 0.5073861555365645,
            "lambda_hazard": 0.5073861555365645,
            "patternability": 0.0,
            "connector": 0.0
          },
          "signature": "c0.01_s0.49_e0.99",
          "window_start": 1656832,
          "window_end": 1657856
        },
        {
          "window_id": 6675,
          "distance": 0.0025387690402567387,
          "metrics": {
            "coherence": 0.013671532656979624,
            "stability": 0.4924917592479551,
            "entropy": 0.9863284673430204,
            "rupture": 0.5075082407520449,
            "lambda_hazard": 0.5075082407520449,
            "patternability": 0.0,
            "connector": 0.0
          },
          "signature": "c0.01_s0.49_e0.99",
          "window_start": 3417600,
          "window_end": 3418624
        },
        {
          "window_id": 5751,
          "distance": 0.0025460352189838886,
          "metrics": {
            "coherence": 0.010905797599254252,
            "stability": 0.4928580148943963,
            "entropy": 0.9890942024007457,
            "rupture": 0.5071419851056037,
            "lambda_hazard": 0.5071419851056037,
            "patternability": 0.0,
            "connector": 0.0
          },
          "signature": "c0.01_s0.49_e0.99",
          "window_start": 2944512,
          "window_end": 2945536
        },
        {
          "window_id": 4829,
          "distance": 0.0025466536171734333,
          "metrics": {
            "coherence": 0.01314089741982849,
            "stability": 0.4926138444634355,
            "entropy": 0.9868591025801715,
            "rupture": 0.5073861555365645,
            "lambda_hazard": 0.5073861555365645,
            "patternability": 0.0,
            "connector": 0.0
          },
          "signature": "c0.01_s0.49_e0.99",
          "window_start": 2472448,
          "window_end": 2473472
        },
        {
          "window_id": 3285,
          "distance": 0.002554363338276744,
          "metrics": {
            "coherence": 0.011433761967797329,
            "stability": 0.4928580148943963,
            "entropy": 0.9885662380322027,
            "rupture": 0.5071419851056037,
            "lambda_hazard": 0.5071419851056037,
            "patternability": 0.0,
            "connector": 0.0
          },
          "signature": "c0.01_s0.49_e0.99",
          "window_start": 1681920,
          "window_end": 1682944
        },
        {
          "window_id": 1242,
          "distance": 0.0025580208748579025,
          "metrics": {
            "coherence": 0.012714624054958601,
            "stability": 0.4927359296789159,
            "entropy": 0.9872853759450414,
            "rupture": 0.5072640703210841,
            "lambda_hazard": 0.5072640703210841,
            "patternability": 0.0,
            "connector": 0.0
          },
          "signature": "c0.01_s0.49_e0.99",
          "window_start": 635904,
          "window_end": 636928
        },
        {
          "window_id": 1232,
          "distance": 0.0025589619763195515,
          "metrics": {
            "coherence": 0.01441221896451228,
            "stability": 0.4924917592479551,
            "entropy": 0.9855877810354877,
            "rupture": 0.5075082407520449,
            "lambda_hazard": 0.5075082407520449,
            "patternability": 0.0,
            "connector": 0.0
          },
          "signature": "c0.01_s0.49_e0.99",
          "window_start": 630784,
          "window_end": 631808
        },
        {
          "window_id": 3277,
          "distance": 0.0025660479441285133,
          "metrics": {
            "coherence": 0.010819026099144424,
            "stability": 0.4929801001098767,
            "entropy": 0.9891809739008556,
            "rupture": 0.5070198998901233,
            "lambda_hazard": 0.5070198998901233,
            "patternability": 0.0,
            "connector": 0.0
          },
          "signature": "c0.01_s0.49_e0.99",
          "window_start": 1677824,
          "window_end": 1678848
        },
        {
          "window_id": 248,
          "distance": 0.002577155828475952,
          "metrics": {
            "coherence": 0.011522978992444921,
            "stability": 0.4929801001098767,
            "entropy": 0.9884770210075551,
            "rupture": 0.5070198998901233,
            "lambda_hazard": 0.5070198998901233,
            "patternability": 0.0,
            "connector": 0.0
          },
          "signature": "c0.01_s0.49_e0.99",
          "window_start": 126976,
          "window_end": 128000
        }
      ]
    }
  ]
}